<?xml version="1.0"?>
<CoveragePattern
  codeIdentifier="BP7UtilitySrvcsDirectDamage"
  coverageCategory="BP7ClassificationAddlGrp"
  coverageSubtype="BP7ClassificationCov"
  coveredPartyType="ThirdParty"
  existence="Electable"
  lookupTableName="BP7ClassificationCov"
  owningEntityType="BP7Classification"
  policyLinePattern="BP7Line"
  priority="1210"
  public-id="BP7UtilitySrvcsDirectDamage"
  referenceDateByType="PolicyTerm">
  <CovTerms>
    <DirectCovTermPattern
      aggregationModel="po"
      codeIdentifier="BP7Limit33"
      coverageColumn="DirectTerm1"
      lookupTableName="BP7ClassificationCovTerm"
      modelType="Limit"
      priority="10"
      public-id="BP7Limit33"
      required="false"
      restrictionModel="bipd"
      valueType="money">
      <LimitsSet>
        <CovTermLimits
          codeIdentifier="BP7Limit33USD"
          currency="usd"
          defaultValue="0"
          minVal="0.0"
          public-id="BP7Limit33USD"/>
      </LimitsSet>
    </DirectCovTermPattern>
    <OptionCovTermPattern
      aggregationModel="po"
      choiceLookupTableName="BP7ClassificationCovOpt"
      codeIdentifier="BP7WaterSupply"
      coverageColumn="ChoiceTerm1"
      lookupTableName="BP7ClassificationCovTerm"
      modelType="Other"
      priority="20"
      public-id="BP7WaterSupply"
      required="true"
      restrictionModel="bipd"
      valueType="other">
      <Options>
        <CovTermOpt
          codeIdentifier="z10hss53l2lgpbaus6ed4rrbg59"
          optionCode="NoCoverage"
          priority="10"
          public-id="z10hss53l2lgpbaus6ed4rrbg59"
          value="0"/>
        <CovTermOpt
          codeIdentifier="z2ij6j6bf4qfr8vg4f16jhej7k8"
          optionCode="PublicUtility"
          priority="20"
          public-id="z2ij6j6bf4qfr8vg4f16jhej7k8"
          value="0"/>
        <CovTermOpt
          codeIdentifier="z17hupdrk0j2rbgr443vipcfpub"
          optionCode="OtherThanPublicUtility"
          priority="30"
          public-id="z17hupdrk0j2rbgr443vipcfpub"
          value="0"/>
      </Options>
    </OptionCovTermPattern>
    <OptionCovTermPattern
      aggregationModel="po"
      choiceLookupTableName="BP7ClassificationCovOpt"
      codeIdentifier="BP7CommunicationSupply"
      coverageColumn="ChoiceTerm2"
      lookupTableName="BP7ClassificationCovTerm"
      modelType="Other"
      priority="30"
      public-id="BP7CommunicationSupply"
      required="true"
      restrictionModel="bipd"
      valueType="other">
      <Options>
        <CovTermOpt
          codeIdentifier="zkcg0t2dt3jq32gh5pr5tomufk9"
          optionCode="NoCoverage"
          priority="10"
          public-id="zkcg0t2dt3jq32gh5pr5tomufk9"
          value="0"/>
        <CovTermOpt
          codeIdentifier="z1ogq3lc14cm97hfsh32eqsn9h8"
          optionCode="PublicUtility_IncludingOverheadCommunicationLines"
          priority="20"
          public-id="z1ogq3lc14cm97hfsh32eqsn9h8"
          value="0"/>
        <CovTermOpt
          codeIdentifier="zmhiu9b7ehm1u35gio872b54mga"
          optionCode="OtherThanPublicUtility_IncludingOverheadCommunicationLines"
          priority="30"
          public-id="zmhiu9b7ehm1u35gio872b54mga"
          value="0"/>
        <CovTermOpt
          codeIdentifier="z88jev87ukanh7outp5fdkcffs8"
          optionCode="PublicUtility_NotIncludingOverheadCommunicationLines"
          priority="40"
          public-id="z88jev87ukanh7outp5fdkcffs8"
          value="0"/>
        <CovTermOpt
          codeIdentifier="z6dhicqape03708bbt5ieh664u9"
          optionCode="OtherThanPublicUtility_NotIncludingOverheadCommunicationLines"
          priority="50"
          public-id="z6dhicqape03708bbt5ieh664u9"
          value="0"/>
      </Options>
    </OptionCovTermPattern>
    <OptionCovTermPattern
      aggregationModel="po"
      choiceLookupTableName="BP7ClassificationCovOpt"
      codeIdentifier="BP7PowerSupply"
      coverageColumn="ChoiceTerm3"
      lookupTableName="BP7ClassificationCovTerm"
      modelType="Other"
      priority="40"
      public-id="BP7PowerSupply"
      required="true"
      restrictionModel="bipd"
      valueType="other">
      <Options>
        <CovTermOpt
          codeIdentifier="znnii05plo6hr47koee27u03he8"
          optionCode="NoCoverage"
          priority="10"
          public-id="znnii05plo6hr47koee27u03he8"
          value="0"/>
        <CovTermOpt
          codeIdentifier="zuti4usp0oa5oedbamrf348838b"
          optionCode="PublicUtility_IncludingOverheadPowerTransmission"
          priority="20"
          public-id="zuti4usp0oa5oedbamrf348838b"
          value="0"/>
        <CovTermOpt
          codeIdentifier="zkogqpj7i9utd3rc5iu4b4c015a"
          optionCode="OtherThanPublicUtility_IncludingOverheadPowerTransmission"
          priority="30"
          public-id="zkogqpj7i9utd3rc5iu4b4c015a"
          value="0"/>
        <CovTermOpt
          codeIdentifier="z6gia4i4ct6nsb93rlkm3417bp8"
          optionCode="PublicUtility_NotIncludingOverheadPowerTransmission"
          priority="40"
          public-id="z6gia4i4ct6nsb93rlkm3417bp8"
          value="0"/>
        <CovTermOpt
          codeIdentifier="zjfjetjbohl5fblvbgrmcm6jghb"
          optionCode="OtherThanPublicUtility_NotIncludingOverheadPowerTransmission"
          priority="50"
          public-id="zjfjetjbohl5fblvbgrmcm6jghb"
          value="0"/>
      </Options>
    </OptionCovTermPattern>
  </CovTerms>
</CoveragePattern>