<?xml version="1.0"?>
<CoveragePattern
  codeIdentifier="Vacancy_EXT"
  coverageCategory="BP7BuildingCondGrp"
  coverageSubtype="BP7BuildingCov"
  coveredPartyType="FirstParty"
  existence="Required"
  lookupTableName="BP7BuildingCov"
  owningEntityType="BP7Building"
  policyLinePattern="BP7Line"
  priority="5360"
  public-id="Vacancy_EXT"
  referenceDateByType="PolicyTerm">
  <AvailabilityScript><![CDATA[return BP7Building.vacancyPermitAvailable()]]></AvailabilityScript>
  <CovTerms>
    <GenericCovTermPattern
      codeIdentifier="EndDate_EXT"
      coverageColumn="DateTerm2"
      lookupTableName="BP7BuildingCovTerm"
      modelType="Other"
      priority="300"
      public-id="EndDate_EXT"
      required="true"/>
    <GenericCovTermPattern
      codeIdentifier="StartDate_EXT"
      coverageColumn="DateTerm1"
      lookupTableName="BP7BuildingCovTerm"
      modelType="Other"
      priority="200"
      public-id="StartDate_EXT"
      required="true"/>
    <OptionCovTermPattern
      aggregationModel="po"
      choiceLookupTableName="BP7BuildingCovOpt"
      codeIdentifier="BP7ExceptedCausesofLoss_EXT"
      coverageColumn="ChoiceTerm1"
      lookupTableName="BP7BuildingCovTerm"
      modelType="Other"
      priority="100"
      public-id="BP7ExceptedCausesofLoss_EXT"
      required="true"
      restrictionModel="bipd"
      valueType="other">
      <DefaultsSet>
        <CovTermDefault
          codeIdentifier="zlui06h4fi1in4ltvuasggq2009"
          defaultValue="None_EXT"
          public-id="zlui06h4fi1in4ltvuasggq2009"/>
      </DefaultsSet>
      <Options>
        <CovTermOpt
          codeIdentifier="z7jjk3e6hv5qu4ltrpcflgbtqqa"
          optionCode="None_EXT"
          priority="100"
          public-id="z7jjk3e6hv5qu4ltrpcflgbtqqa"
          value="0"/>
        <CovTermOpt
          codeIdentifier="zn5j2jii7vn8c9qgdl810o8fpt8"
          optionCode="Vandalism_EXT"
          priority="400"
          public-id="zn5j2jii7vn8c9qgdl810o8fpt8"
          value="0"/>
        <CovTermOpt
          codeIdentifier="zpugsn31k0kpjcobmirla7t2bra"
          optionCode="SprinklerLeakageandVandalism_EXT"
          priority="300"
          public-id="zpugsn31k0kpjcobmirla7t2bra"
          value="0"/>
        <CovTermOpt
          codeIdentifier="zangkeqef1n6e4tiui9vgmtmjc8"
          optionCode="SprinklerLeakage_EXT"
          priority="200"
          public-id="zangkeqef1n6e4tiui9vgmtmjc8"
          value="0"/>
      </Options>
    </OptionCovTermPattern>
  </CovTerms>
</CoveragePattern>