<?xml version="1.0"?>
<import>
  <HOCoverageLookup_HOE public-id="zurh0atvcmsl7avtb2okkjrahja">
    <Availability>Available</Availability>
    <CoveragePatternCode>DPDW_Alteration_HOE_Ext</CoveragePatternCode>
    <EndEffectiveDate/>
    <HOPolicyType/>
    <JobType/>
    <PolicyLinePatternCode>HomeownersLine_HOE</PolicyLinePatternCode>
    <StartEffectiveDate>2001-01-01 00:00:00.000</StartEffectiveDate>
    <State/>
    <UWCompanyCode/>
  </HOCoverageLookup_HOE>
  <HOCovTermLookup_HOE public-id="zqqiaace3bruu0coaglnskrg23b">
    <Availability>Available</Availability>
    <CovTermPatternCode>DPDW_AlterationLimit_HOE</CovTermPatternCode>
    <EndEffectiveDate/>
    <HOPolicyType/>
    <JobType/>
    <PolicyLinePatternCode>HomeownersLine_HOE</PolicyLinePatternCode>
    <StartEffectiveDate>2001-01-01 00:00:00.000</StartEffectiveDate>
    <State/>
    <UWCompanyCode/>
  </HOCovTermLookup_HOE>
  <HOCovTermOptLookup_HOE public-id="zrnjs3t1a4qfu9emjpqk68ho379">
    <Availability>Available</Availability>
    <CovTermOptCode>zfjisag1e1udf6gc6fm49vjm3r8</CovTermOptCode>
    <CovTermPatternCode>DPDW_AlterationLimit_HOE</CovTermPatternCode>
    <Currency/>
    <EndEffectiveDate/>
    <HOPolicyType/>
    <JobType/>
    <StartEffectiveDate>2001-01-01 00:00:00.000</StartEffectiveDate>
    <State/>
    <UWCompanyCode/>
  </HOCovTermOptLookup_HOE>
</import>