<?xml version="1.0"?>
<import>
  <ExclusionLookup_HOE public-id="ztqgapnlkapndark1cj5rr68kna">
    <Availability>Available</Availability>
    <EndEffectiveDate/>
    <ExclusionPatternCode>HODW_RejectionOfWindstrom_HOE_Ext</ExclusionPatternCode>
    <HOPolicyType>DP3_Ext</HOPolicyType>
    <JobType/>
    <PolicyLinePatternCode>HomeownersLine_HOE</PolicyLinePatternCode>
    <StartEffectiveDate>2001-01-01 00:00:00.000</StartEffectiveDate>
    <State>FL</State>
    <UWCompanyCode/>
  </ExclusionLookup_HOE>
</import>