<?xml version="1.0"?>
<import>
  <HOCoverageLookup_HOE public-id="zt3jkhs6og1p5268k38iup9vmeb">
    <Availability>Available</Availability>
    <CoveragePatternCode>HODW_LimitedScreenCov_HOE_Ext</CoveragePatternCode>
    <EndEffectiveDate/>
    <HOPolicyType>HO3</HOPolicyType>
    <JobType/>
    <PolicyLinePatternCode>HomeownersLine_HOE</PolicyLinePatternCode>
    <StartEffectiveDate>2000-01-01 00:00:00.000</StartEffectiveDate>
    <State>FL</State>
    <UWCompanyCode/>
  </HOCoverageLookup_HOE>
  <HOCoverageLookup_HOE public-id="zn4g4s4v0dlrq4ve00dp99pgbea">
    <Availability>Available</Availability>
    <CoveragePatternCode>HODW_LimitedScreenCov_HOE_Ext</CoveragePatternCode>
    <EndEffectiveDate/>
    <HOPolicyType>DP3_Ext</HOPolicyType>
    <JobType/>
    <PolicyLinePatternCode>HomeownersLine_HOE</PolicyLinePatternCode>
    <StartEffectiveDate>2000-01-01 00:00:00.000</StartEffectiveDate>
    <State>FL</State>
    <UWCompanyCode/>
  </HOCoverageLookup_HOE>
</import>