<?xml version="1.0"?>
<import>
  <HOCoverageLookup_HOE public-id="z9rg2kgjl1l779jbo44cq2lhf6a">
    <Availability>Available</Availability>
    <CoveragePatternCode>HODW_BusinessProperty_HOE_Ext</CoveragePatternCode>
    <EndEffectiveDate/>
    <HOPolicyType>HO3</HOPolicyType>
    <JobType/>
    <PolicyLinePatternCode>HomeownersLine_HOE</PolicyLinePatternCode>
    <StartEffectiveDate>2001-01-01 00:00:00.000</StartEffectiveDate>
    <State>NC</State>
    <UWCompanyCode/>
  </HOCoverageLookup_HOE>
  <HOCoverageLookup_HOE public-id="zo3gu5gv58vrt3lmun20nikaf39">
    <Availability>Available</Availability>
    <CoveragePatternCode>HODW_BusinessProperty_HOE_Ext</CoveragePatternCode>
    <EndEffectiveDate/>
    <HOPolicyType>HO6</HOPolicyType>
    <JobType/>
    <PolicyLinePatternCode>HomeownersLine_HOE</PolicyLinePatternCode>
    <StartEffectiveDate>2001-01-01 00:00:00.000</StartEffectiveDate>
    <State>NC</State>
    <UWCompanyCode/>
  </HOCoverageLookup_HOE>
  <HOCoverageLookup_HOE public-id="zo6hechdufrpqc82d3dof75s518">
    <Availability>Available</Availability>
    <CoveragePatternCode>HODW_BusinessProperty_HOE_Ext</CoveragePatternCode>
    <EndEffectiveDate/>
    <HOPolicyType>HO4</HOPolicyType>
    <JobType/>
    <PolicyLinePatternCode>HomeownersLine_HOE</PolicyLinePatternCode>
    <StartEffectiveDate>2001-01-01 00:00:00.000</StartEffectiveDate>
    <State>NC</State>
    <UWCompanyCode/>
  </HOCoverageLookup_HOE>
</import>