<?xml version="1.0"?>
<import>
  <HOCovTermOptLookup_HOE public-id="z5ahuea7mq6urbic7dun1j9sctb">
    <Availability>Available</Availability>
    <CovTermOptCode>zabh0dsgnkpsg5dd8i81m91li79</CovTermOptCode>
    <CovTermPatternCode>HOLI_AggLimit_HOE</CovTermPatternCode>
    <Currency>usd</Currency>
    <EndEffectiveDate/>
    <HOPolicyType/>
    <JobType/>
    <StartEffectiveDate>2000-01-01 00:00:00.000</StartEffectiveDate>
    <State>NC</State>
    <UWCompanyCode/>
  </HOCovTermOptLookup_HOE>
  <HOCoverageLookup_HOE public-id="zi4i6thin3otud9ffnt9krq5go9">
    <Availability>Unavailable</Availability>
    <CoveragePatternCode>HOLI_FungiCov_HOE</CoveragePatternCode>
    <EndEffectiveDate/>
    <HOPolicyType/>
    <JobType/>
    <PolicyLinePatternCode>HomeownersLine_HOE</PolicyLinePatternCode>
    <StartEffectiveDate>2000-01-01 00:00:00.000</StartEffectiveDate>
    <State>NC</State>
    <UWCompanyCode/>
  </HOCoverageLookup_HOE>
</import>