<?xml version="1.0"?>
<import>
  <BP7BuildingLimitOfInsRelativityFactor public-id="zg6ja68266fgr89iat90rpi3ca9">
    <BuildingLimit>1</BuildingLimit>
    <RelativityGroup>A</RelativityGroup>
    <RelativityFactor>1.678</RelativityFactor>
  </BP7BuildingLimitOfInsRelativityFactor>
  <BP7BuildingLimitOfInsRelativityFactor public-id="z7gig3sipuaof7udehaoqnlbkda">
    <BuildingLimit>50000</BuildingLimit>
    <RelativityGroup>A</RelativityGroup>
    <RelativityFactor>1.678</RelativityFactor>
  </BP7BuildingLimitOfInsRelativityFactor>
  <BP7BuildingLimitOfInsRelativityFactor public-id="z65gstg2svu5q7vh2ccge0sq559">
    <BuildingLimit>75000</BuildingLimit>
    <RelativityGroup>A</RelativityGroup>
    <RelativityFactor>1.525</RelativityFactor>
  </BP7BuildingLimitOfInsRelativityFactor>
  <BP7BuildingLimitOfInsRelativityFactor public-id="zhsjoepk9u9b4bfsihg13uqmdva">
    <BuildingLimit>100000</BuildingLimit>
    <RelativityGroup>A</RelativityGroup>
    <RelativityFactor>1.347</RelativityFactor>
  </BP7BuildingLimitOfInsRelativityFactor>
  <BP7BuildingLimitOfInsRelativityFactor public-id="z6iis5n97m9vvd0dn3hro4u2k1b">
    <BuildingLimit>125000</BuildingLimit>
    <RelativityGroup>A</RelativityGroup>
    <RelativityFactor>1.224</RelativityFactor>
  </BP7BuildingLimitOfInsRelativityFactor>
  <BP7BuildingLimitOfInsRelativityFactor public-id="z31g6qvnnchiv3uq4kf6oo091bb">
    <BuildingLimit>150000</BuildingLimit>
    <RelativityGroup>A</RelativityGroup>
    <RelativityFactor>1.132</RelativityFactor>
  </BP7BuildingLimitOfInsRelativityFactor>
  <BP7BuildingLimitOfInsRelativityFactor public-id="zv5hunrf3mmu0747327rmpas68b">
    <BuildingLimit>175000</BuildingLimit>
    <RelativityGroup>A</RelativityGroup>
    <RelativityFactor>1.059</RelativityFactor>
  </BP7BuildingLimitOfInsRelativityFactor>
  <BP7BuildingLimitOfInsRelativityFactor public-id="zhege3slrahaa7smm2alf4rsqd9">
    <BuildingLimit>200000</BuildingLimit>
    <RelativityGroup>A</RelativityGroup>
    <RelativityFactor>1</RelativityFactor>
  </BP7BuildingLimitOfInsRelativityFactor>
  <BP7BuildingLimitOfInsRelativityFactor public-id="zaoh4hb6ihlfqbserniq3no6ij8">
    <BuildingLimit>225000</BuildingLimit>
    <RelativityGroup>A</RelativityGroup>
    <RelativityFactor>0.951</RelativityFactor>
  </BP7BuildingLimitOfInsRelativityFactor>
  <BP7BuildingLimitOfInsRelativityFactor public-id="zphgam7n9otkm2t49nadi4c092b">
    <BuildingLimit>250000</BuildingLimit>
    <RelativityGroup>A</RelativityGroup>
    <RelativityFactor>0.908</RelativityFactor>
  </BP7BuildingLimitOfInsRelativityFactor>
  <BP7BuildingLimitOfInsRelativityFactor public-id="zt4ge5v6lfpt08ivj1qpqdv3u8a">
    <BuildingLimit>275000</BuildingLimit>
    <RelativityGroup>A</RelativityGroup>
    <RelativityFactor>0.872</RelativityFactor>
  </BP7BuildingLimitOfInsRelativityFactor>
  <BP7BuildingLimitOfInsRelativityFactor public-id="z4lhq85bhfdhlbcdrga85h057fa">
    <BuildingLimit>300000</BuildingLimit>
    <RelativityGroup>A</RelativityGroup>
    <RelativityFactor>0.84</RelativityFactor>
  </BP7BuildingLimitOfInsRelativityFactor>
  <BP7BuildingLimitOfInsRelativityFactor public-id="zc5jqshb8locbcvr4v130ksutaa">
    <BuildingLimit>325000</BuildingLimit>
    <RelativityGroup>A</RelativityGroup>
    <RelativityFactor>0.812</RelativityFactor>
  </BP7BuildingLimitOfInsRelativityFactor>
  <BP7BuildingLimitOfInsRelativityFactor public-id="z7eguelcfj8a2eqroue7fs6h13b">
    <BuildingLimit>350000</BuildingLimit>
    <RelativityGroup>A</RelativityGroup>
    <RelativityFactor>0.786</RelativityFactor>
  </BP7BuildingLimitOfInsRelativityFactor>
  <BP7BuildingLimitOfInsRelativityFactor public-id="z0jhovmjg7b5j2jpf9lbbk7aln9">
    <BuildingLimit>375000</BuildingLimit>
    <RelativityGroup>A</RelativityGroup>
    <RelativityFactor>0.763</RelativityFactor>
  </BP7BuildingLimitOfInsRelativityFactor>
  <BP7BuildingLimitOfInsRelativityFactor public-id="zn3ju92unekndd0rlt0t469r3v8">
    <BuildingLimit>400000</BuildingLimit>
    <RelativityGroup>A</RelativityGroup>
    <RelativityFactor>0.742</RelativityFactor>
  </BP7BuildingLimitOfInsRelativityFactor>
  <BP7BuildingLimitOfInsRelativityFactor public-id="zckg8v81bi3vf3jpuh3fh9f56b8">
    <BuildingLimit>425000</BuildingLimit>
    <RelativityGroup>A</RelativityGroup>
    <RelativityFactor>0.723</RelativityFactor>
  </BP7BuildingLimitOfInsRelativityFactor>
  <BP7BuildingLimitOfInsRelativityFactor public-id="z10h2vbimu4ru2nr5nq6ntgjkd9">
    <BuildingLimit>450000</BuildingLimit>
    <RelativityGroup>A</RelativityGroup>
    <RelativityFactor>0.706</RelativityFactor>
  </BP7BuildingLimitOfInsRelativityFactor>
  <BP7BuildingLimitOfInsRelativityFactor public-id="z1sh6o0ocgdsdfecf83fpi8iot9">
    <BuildingLimit>475000</BuildingLimit>
    <RelativityGroup>A</RelativityGroup>
    <RelativityFactor>0.689</RelativityFactor>
  </BP7BuildingLimitOfInsRelativityFactor>
  <BP7BuildingLimitOfInsRelativityFactor public-id="zlsh0cagtlsb12cjd7s3fog16ob">
    <BuildingLimit>500000</BuildingLimit>
    <RelativityGroup>A</RelativityGroup>
    <RelativityFactor>0.674</RelativityFactor>
  </BP7BuildingLimitOfInsRelativityFactor>
  <BP7BuildingLimitOfInsRelativityFactor public-id="zrfh0utc1n36055nl3o5aaunb28">
    <BuildingLimit>550000</BuildingLimit>
    <RelativityGroup>A</RelativityGroup>
    <RelativityFactor>0.647</RelativityFactor>
  </BP7BuildingLimitOfInsRelativityFactor>
  <BP7BuildingLimitOfInsRelativityFactor public-id="zppj2olfb2flg6lm0fo52c1tbvb">
    <BuildingLimit>600000</BuildingLimit>
    <RelativityGroup>A</RelativityGroup>
    <RelativityFactor>0.623</RelativityFactor>
  </BP7BuildingLimitOfInsRelativityFactor>
  <BP7BuildingLimitOfInsRelativityFactor public-id="z6si2nf5078fd9dhf5c5q8reri8">
    <BuildingLimit>650000</BuildingLimit>
    <RelativityGroup>A</RelativityGroup>
    <RelativityFactor>0.602</RelativityFactor>
  </BP7BuildingLimitOfInsRelativityFactor>
  <BP7BuildingLimitOfInsRelativityFactor public-id="zllg0a4f48t1l18eht0ijok266b">
    <BuildingLimit>700000</BuildingLimit>
    <RelativityGroup>A</RelativityGroup>
    <RelativityFactor>0.583</RelativityFactor>
  </BP7BuildingLimitOfInsRelativityFactor>
  <BP7BuildingLimitOfInsRelativityFactor public-id="zb5iuvn6q515sdsqrf7i9suglv8">
    <BuildingLimit>750000</BuildingLimit>
    <RelativityGroup>A</RelativityGroup>
    <RelativityFactor>0.566</RelativityFactor>
  </BP7BuildingLimitOfInsRelativityFactor>
  <BP7BuildingLimitOfInsRelativityFactor public-id="zvkgu1ehpcvbn80p6n4i0ga3u69">
    <BuildingLimit>800000</BuildingLimit>
    <RelativityGroup>A</RelativityGroup>
    <RelativityFactor>0.551</RelativityFactor>
  </BP7BuildingLimitOfInsRelativityFactor>
  <BP7BuildingLimitOfInsRelativityFactor public-id="z07gccfr59cie754n2opo4glk6b">
    <BuildingLimit>850000</BuildingLimit>
    <RelativityGroup>A</RelativityGroup>
    <RelativityFactor>0.537</RelativityFactor>
  </BP7BuildingLimitOfInsRelativityFactor>
  <BP7BuildingLimitOfInsRelativityFactor public-id="zocja3hlq9nr50r672nbge0pgd9">
    <BuildingLimit>900000</BuildingLimit>
    <RelativityGroup>A</RelativityGroup>
    <RelativityFactor>0.524</RelativityFactor>
  </BP7BuildingLimitOfInsRelativityFactor>
  <BP7BuildingLimitOfInsRelativityFactor public-id="zfmhgtqpp1l6e5098k7ufrao4oa">
    <BuildingLimit>950000</BuildingLimit>
    <RelativityGroup>A</RelativityGroup>
    <RelativityFactor>0.512</RelativityFactor>
  </BP7BuildingLimitOfInsRelativityFactor>
  <BP7BuildingLimitOfInsRelativityFactor public-id="zckiego0gnum34uitqphfhp13gb">
    <BuildingLimit>1000000</BuildingLimit>
    <RelativityGroup>A</RelativityGroup>
    <RelativityFactor>0.5</RelativityFactor>
  </BP7BuildingLimitOfInsRelativityFactor>
  <BP7BuildingLimitOfInsRelativityFactor public-id="z48gu372e5o5ldlqagcqphsv3t9">
    <BuildingLimit>999999999</BuildingLimit>
    <RelativityGroup>A</RelativityGroup>
    <RelativityFactor>0.5</RelativityFactor>
  </BP7BuildingLimitOfInsRelativityFactor>
</import>
